pydantic_cacheable_model/__init__.py
pydantic_cacheable_model/py.typed
pydantic_cacheable_model-2.0.1.dist-info/WHEEL
pydantic_cacheable_model-2.0.1.dist-info/METADATA
pydantic_cacheable_model-2.0.1.dist-info/RECORD
