Metadata-Version: 2.3
Name: pydantic-cacheable-model
Version: 2.0.1
Summary: Small Pydantic helpers for cacheable models
Author: J.I. Cruz
Author-email: J.I. Cruz <ji@jicruz.com>
Requires-Dist: pydantic>=2.11.7
Requires-Dist: typing-extensions>=4.6 ; python_full_version < '3.11'
Requires-Python: >=3.10
